pyjokes_hebrew
