Metadata-Version: 1.1
Name: pyjokes-hebrew
Version: 0.0.5
Summary: with this module you can get a random joke in hebrew!!!!!!!
Home-page: https://lamed-oti2.ml/
Author: Kobi Shutzi
Author-email: shutzi@gmail.com
License: MIT
Keywords: pyjokes
Platform: UNKNOWN
Classifier: Development Status :: 5 - Production/Stable
Classifier: Intended Audience :: Education
Classifier: Operating System :: Microsoft :: Windows :: Windows 10
Classifier: License :: OSI Approved :: MIT License
Classifier: Programming Language :: Python :: 3
